fcgiproto/__init__.py
fcgiproto/connection.py
fcgiproto/constants.py
fcgiproto/events.py
fcgiproto/exceptions.py
fcgiproto/records.py
fcgiproto/states.py
fcgiproto/connection.pyi
fcgiproto-1.0.2.dist-info/top_level.txt
fcgiproto-1.0.2.dist-info/METADATA
fcgiproto-1.0.2.dist-info/DESCRIPTION.rst
fcgiproto-1.0.2.dist-info/metadata.json
fcgiproto-1.0.2.dist-info/WHEEL
fcgiproto-1.0.2.dist-info/RECORD
