Metadata-Version: 2.0
Name: fcgiproto
Version: 1.0.2
Summary: FastCGI state-machine based protocol implementation
Home-page: https://github.com/agronholm/fcgiproto
Author: Alex Grönholm
Author-email: alex.gronholm@nextday.fi
License: MIT
Keywords: fastcgi http
Platform: UNKNOWN
Classifier: Development Status :: 5 - Production/Stable
Classifier: Intended Audience :: Developers
Classifier: License :: OSI Approved :: MIT License
Classifier: Programming Language :: Python
Classifier: Programming Language :: Python :: 2.7
Classifier: Programming Language :: Python :: 3
Classifier: Programming Language :: Python :: 3.3
Classifier: Programming Language :: Python :: 3.4
Classifier: Programming Language :: Python :: 3.5
